napari_3d_counter/__init__.py
napari_3d_counter/_reader.py
napari_3d_counter/_version.py
napari_3d_counter/_widget.py
napari_3d_counter/aux_functions.py
napari_3d_counter/celltype_config.py
napari_3d_counter/commands.py
napari_3d_counter/napari.yaml
napari_3d_counter/_tests/__init__.py
napari_3d_counter/_tests/bad.csv
napari_3d_counter/_tests/test_aux.py
napari_3d_counter/_tests/test_aux_functions.py
napari_3d_counter/_tests/test_celltype_config.py
napari_3d_counter/_tests/test_commands.py
napari_3d_counter/_tests/test_empty.csv
napari_3d_counter/_tests/test_point.csv
napari_3d_counter/_tests/test_python_gen.py
napari_3d_counter/_tests/test_reader.py
napari_3d_counter/_tests/test_widget.py
napari_3d_counter-0.5.9.dist-info/licenses/LICENSE
napari_3d_counter-0.5.9.dist-info/METADATA
napari_3d_counter-0.5.9.dist-info/WHEEL
napari_3d_counter-0.5.9.dist-info/entry_points.txt
napari_3d_counter-0.5.9.dist-info/top_level.txt
napari_3d_counter-0.5.9.dist-info/RECORD
