Metadata-Version: 2.4
Name: napari-3d-counter
Version: 0.5.9
Summary: A simple plugin for counting objects in 3D images
Home-page: https://github.com/pnewstein/napari-3d-counter
Author: Peter Newstein
Author-email: peternewstein@gmail.com
License: GPL-3.0-or-later
Project-URL: Bug Tracker, https://github.com/pnewstein/napari-3d-counter/issues
Project-URL: Documentation, http://localhost:8001/napari-3d-counter.html
Project-URL: Source Code, https://github.com/pnewstein/napari-3d-counter
Project-URL: User Support, https://github.com/pnewstein/napari-3d-counter/issues
Classifier: Development Status :: 4 - Beta
Classifier: Framework :: napari
Classifier: Intended Audience :: Developers
Classifier: License :: OSI Approved :: GNU General Public License v3 (GPLv3)
Classifier: Operating System :: OS Independent
Classifier: Programming Language :: Python
Classifier: Programming Language :: Python :: 3
Classifier: Programming Language :: Python :: 3 :: Only
Classifier: Programming Language :: Python :: 3.10
Classifier: Programming Language :: Python :: 3.11
Classifier: Programming Language :: Python :: 3.12
Classifier: Topic :: Scientific/Engineering :: Image Processing
Requires-Python: >=3.10
License-File: LICENSE
Requires-Dist: numpy
Requires-Dist: qtpy
Requires-Dist: pandas
Requires-Dist: scikit-image
Requires-Dist: napari==0.6.*
Provides-Extra: testing
Requires-Dist: tox; extra == "testing"
Requires-Dist: pytest; extra == "testing"
Requires-Dist: pytest-cov; extra == "testing"
Requires-Dist: pytest-qt; extra == "testing"
Requires-Dist: pyqt5; extra == "testing"
Dynamic: license-file
